odoo/addons/test_mail_template_attachment_i18n/README.rst
odoo/addons/test_mail_template_attachment_i18n/__init__.py
odoo/addons/test_mail_template_attachment_i18n/__manifest__.py
odoo/addons/test_mail_template_attachment_i18n/i18n/test_mail_template_attachment_i18n.pot
odoo/addons/test_mail_template_attachment_i18n/readme/CONTRIBUTORS.rst
odoo/addons/test_mail_template_attachment_i18n/readme/DESCRIPTION.rst
odoo/addons/test_mail_template_attachment_i18n/static/description/icon.png
odoo/addons/test_mail_template_attachment_i18n/static/description/index.html
odoo/addons/test_mail_template_attachment_i18n/tests/__init__.py
odoo/addons/test_mail_template_attachment_i18n/tests/test_attaching_by_language.py
odoo11_addon_test_mail_template_attachment_i18n-11.0.1.0.0.99.dev7.dist-info/METADATA
odoo11_addon_test_mail_template_attachment_i18n-11.0.1.0.0.99.dev7.dist-info/WHEEL
odoo11_addon_test_mail_template_attachment_i18n-11.0.1.0.0.99.dev7.dist-info/top_level.txt
odoo11_addon_test_mail_template_attachment_i18n-11.0.1.0.0.99.dev7.dist-info/RECORD
